__init__.py
_conversion.py
heathcliff.py
heathcliff-0.1.0.dist-info/METADATA
heathcliff-0.1.0.dist-info/WHEEL
heathcliff-0.1.0.dist-info/top_level.txt
heathcliff-0.1.0.dist-info/RECORD
