Metadata-Version: 2.4
Name: heathcliff
Version: 0.1.0
Summary: Pull features from ArcGIS Feature Servers
Requires-Python: >=3.13
Requires-Dist: httpx>=0.28.1
Requires-Dist: tqdm>=4.67.1
